{"id":"cFPX","dependencies":[{"name":"E:\\frontend\\CyberMonitor\\node_modules\\antd\\package.json","includedInParent":true,"mtime":1536996384191},{"name":"E:\\frontend\\CyberMonitor\\package.json","includedInParent":true,"mtime":1536996456654},{"name":"E:\\frontend\\CyberMonitor\\.babelrc","includedInParent":true,"mtime":1535686769026},{"name":"./Input","loc":{"line":7,"column":21},"parent":"E:\\frontend\\CyberMonitor\\node_modules\\antd\\lib\\input\\index.js","resolved":"E:\\frontend\\CyberMonitor\\node_modules\\antd\\lib\\input\\Input.js"},{"name":"./Group","loc":{"line":11,"column":21},"parent":"E:\\frontend\\CyberMonitor\\node_modules\\antd\\lib\\input\\index.js","resolved":"E:\\frontend\\CyberMonitor\\node_modules\\antd\\lib\\input\\Group.js"},{"name":"./Search","loc":{"line":15,"column":22},"parent":"E:\\frontend\\CyberMonitor\\node_modules\\antd\\lib\\input\\index.js","resolved":"E:\\frontend\\CyberMonitor\\node_modules\\antd\\lib\\input\\Search.js"},{"name":"./TextArea","loc":{"line":19,"column":24},"parent":"E:\\frontend\\CyberMonitor\\node_modules\\antd\\lib\\input\\index.js","resolved":"E:\\frontend\\CyberMonitor\\node_modules\\antd\\lib\\input\\TextArea.js"}],"generated":{"js":"\"use strict\";Object.defineProperty(exports,\"__esModule\",{value:!0});var e=require(\"./Input\"),r=o(e),u=require(\"./Group\"),t=o(u),a=require(\"./Search\"),d=o(a),l=require(\"./TextArea\"),f=o(l);function o(e){return e&&e.__esModule?e:{default:e}}r.default.Group=t.default,r.default.Search=d.default,r.default.TextArea=f.default,exports.default=r.default,module.exports=exports.default;","map":{"mappings":[{"source":"..\\node_modules\\antd\\lib\\input\\index.js","original":{"line":1,"column":0},"generated":{"line":1,"column":0}},{"source":"..\\node_modules\\antd\\lib\\input\\index.js","original":{"line":3,"column":0},"generated":{"line":1,"column":13}},{"source":"..\\node_modules\\antd\\lib\\input\\index.js","original":{"line":3,"column":0},"generated":{"line":1,"column":20}},{"source":"..\\node_modules\\antd\\lib\\input\\index.js","original":{"line":3,"column":0},"generated":{"line":1,"column":35}},{"source":"..\\node_modules\\antd\\lib\\input\\index.js","original":{"line":3,"column":0},"generated":{"line":1,"column":43}},{"source":"..\\node_modules\\antd\\lib\\input\\index.js","original":{"line":3,"column":0},"generated":{"line":1,"column":56}},{"source":"..\\node_modules\\antd\\lib\\input\\index.js","original":{"line":4,"column":0},"generated":{"line":1,"column":57}},{"source":"..\\node_modules\\antd\\lib\\input\\index.js","original":{"line":4,"column":0},"generated":{"line":1,"column":64}},{"source":"..\\node_modules\\antd\\lib\\input\\index.js","original":{"line":7,"column":0},"generated":{"line":1,"column":68}},{"source":"..\\node_modules\\antd\\lib\\input\\index.js","original":{"line":7,"column":0},"generated":{"line":1,"column":72}},{"source":"..\\node_modules\\antd\\lib\\input\\index.js","original":{"line":7,"column":0},"generated":{"line":1,"column":74}},{"source":"..\\node_modules\\antd\\lib\\input\\index.js","original":{"line":7,"column":0},"generated":{"line":1,"column":82}},{"source":"..\\node_modules\\antd\\lib\\input\\index.js","original":{"line":9,"column":0},"generated":{"line":1,"column":93}},{"source":"..\\node_modules\\antd\\lib\\input\\index.js","original":{"line":9,"column":0},"generated":{"line":1,"column":95}},{"source":"..\\node_modules\\antd\\lib\\input\\index.js","original":{"line":9,"column":0},"generated":{"line":1,"column":97}},{"source":"..\\node_modules\\antd\\lib\\input\\index.js","original":{"line":11,"column":0},"generated":{"line":1,"column":100}},{"source":"..\\node_modules\\antd\\lib\\input\\index.js","original":{"line":11,"column":0},"generated":{"line":1,"column":102}},{"source":"..\\node_modules\\antd\\lib\\input\\index.js","original":{"line":11,"column":0},"generated":{"line":1,"column":110}},{"source":"..\\node_modules\\antd\\lib\\input\\index.js","original":{"line":13,"column":0},"generated":{"line":1,"column":121}},{"source":"..\\node_modules\\antd\\lib\\input\\index.js","original":{"line":13,"column":0},"generated":{"line":1,"column":123}},{"source":"..\\node_modules\\antd\\lib\\input\\index.js","original":{"line":13,"column":0},"generated":{"line":1,"column":125}},{"source":"..\\node_modules\\antd\\lib\\input\\index.js","original":{"line":15,"column":0},"generated":{"line":1,"column":128}},{"source":"..\\node_modules\\antd\\lib\\input\\index.js","original":{"line":15,"column":0},"generated":{"line":1,"column":130}},{"source":"..\\node_modules\\antd\\lib\\input\\index.js","original":{"line":15,"column":0},"generated":{"line":1,"column":138}},{"source":"..\\node_modules\\antd\\lib\\input\\index.js","original":{"line":17,"column":0},"generated":{"line":1,"column":150}},{"source":"..\\node_modules\\antd\\lib\\input\\index.js","original":{"line":17,"column":0},"generated":{"line":1,"column":152}},{"source":"..\\node_modules\\antd\\lib\\input\\index.js","original":{"line":17,"column":0},"generated":{"line":1,"column":154}},{"source":"..\\node_modules\\antd\\lib\\input\\index.js","original":{"line":19,"column":0},"generated":{"line":1,"column":157}},{"source":"..\\node_modules\\antd\\lib\\input\\index.js","original":{"line":19,"column":0},"generated":{"line":1,"column":159}},{"source":"..\\node_modules\\antd\\lib\\input\\index.js","original":{"line":19,"column":0},"generated":{"line":1,"column":167}},{"source":"..\\node_modules\\antd\\lib\\input\\index.js","original":{"line":21,"column":0},"generated":{"line":1,"column":181}},{"source":"..\\node_modules\\antd\\lib\\input\\index.js","original":{"line":21,"column":0},"generated":{"line":1,"column":183}},{"source":"..\\node_modules\\antd\\lib\\input\\index.js","original":{"line":21,"column":0},"generated":{"line":1,"column":185}},{"source":"..\\node_modules\\antd\\lib\\input\\index.js","original":{"line":23,"column":0},"generated":{"line":1,"column":188}},{"source":"..\\node_modules\\antd\\lib\\input\\index.js","original":{"line":23,"column":0},"generated":{"line":1,"column":197}},{"source":"..\\node_modules\\antd\\lib\\input\\index.js","original":{"line":23,"column":0},"generated":{"line":1,"column":199}},{"source":"..\\node_modules\\antd\\lib\\input\\index.js","original":{"line":23,"column":0},"generated":{"line":1,"column":202}},{"source":"..\\node_modules\\antd\\lib\\input\\index.js","original":{"line":23,"column":0},"generated":{"line":1,"column":209}},{"source":"..\\node_modules\\antd\\lib\\input\\index.js","original":{"line":23,"column":0},"generated":{"line":1,"column":212}},{"source":"..\\node_modules\\antd\\lib\\input\\index.js","original":{"line":23,"column":0},"generated":{"line":1,"column":214}},{"source":"..\\node_modules\\antd\\lib\\input\\index.js","original":{"line":23,"column":0},"generated":{"line":1,"column":225}},{"source":"..\\node_modules\\antd\\lib\\input\\index.js","original":{"line":23,"column":0},"generated":{"line":1,"column":227}},{"source":"..\\node_modules\\antd\\lib\\input\\index.js","original":{"line":23,"column":0},"generated":{"line":1,"column":228}},{"source":"..\\node_modules\\antd\\lib\\input\\index.js","original":{"line":23,"column":0},"generated":{"line":1,"column":236}},{"source":"..\\node_modules\\antd\\lib\\input\\index.js","original":{"line":25,"column":0},"generated":{"line":1,"column":239}},{"source":"..\\node_modules\\antd\\lib\\input\\index.js","original":{"line":25,"column":0},"generated":{"line":1,"column":241}},{"source":"..\\node_modules\\antd\\lib\\input\\index.js","original":{"line":25,"column":0},"generated":{"line":1,"column":249}},{"source":"..\\node_modules\\antd\\lib\\input\\index.js","original":{"line":25,"column":0},"generated":{"line":1,"column":255}},{"source":"..\\node_modules\\antd\\lib\\input\\index.js","original":{"line":25,"column":0},"generated":{"line":1,"column":257}},{"source":"..\\node_modules\\antd\\lib\\input\\index.js","original":{"line":26,"column":0},"generated":{"line":1,"column":265}},{"source":"..\\node_modules\\antd\\lib\\input\\index.js","original":{"line":26,"column":0},"generated":{"line":1,"column":267}},{"source":"..\\node_modules\\antd\\lib\\input\\index.js","original":{"line":26,"column":0},"generated":{"line":1,"column":275}},{"source":"..\\node_modules\\antd\\lib\\input\\index.js","original":{"line":26,"column":0},"generated":{"line":1,"column":282}},{"source":"..\\node_modules\\antd\\lib\\input\\index.js","original":{"line":26,"column":0},"generated":{"line":1,"column":284}},{"source":"..\\node_modules\\antd\\lib\\input\\index.js","original":{"line":27,"column":0},"generated":{"line":1,"column":292}},{"source":"..\\node_modules\\antd\\lib\\input\\index.js","original":{"line":27,"column":0},"generated":{"line":1,"column":294}},{"source":"..\\node_modules\\antd\\lib\\input\\index.js","original":{"line":27,"column":0},"generated":{"line":1,"column":302}},{"source":"..\\node_modules\\antd\\lib\\input\\index.js","original":{"line":27,"column":0},"generated":{"line":1,"column":311}},{"source":"..\\node_modules\\antd\\lib\\input\\index.js","original":{"line":27,"column":0},"generated":{"line":1,"column":313}},{"source":"..\\node_modules\\antd\\lib\\input\\index.js","original":{"line":28,"column":0},"generated":{"line":1,"column":321}},{"source":"..\\node_modules\\antd\\lib\\input\\index.js","original":{"line":28,"column":0},"generated":{"line":1,"column":329}},{"source":"..\\node_modules\\antd\\lib\\input\\index.js","original":{"line":28,"column":0},"generated":{"line":1,"column":337}},{"source":"..\\node_modules\\antd\\lib\\input\\index.js","original":{"line":28,"column":0},"generated":{"line":1,"column":339}},{"source":"..\\node_modules\\antd\\lib\\input\\index.js","original":{"line":29,"column":0},"generated":{"line":1,"column":347}},{"source":"..\\node_modules\\antd\\lib\\input\\index.js","original":{"line":29,"column":0},"generated":{"line":1,"column":354}},{"source":"..\\node_modules\\antd\\lib\\input\\index.js","original":{"line":29,"column":0},"generated":{"line":1,"column":362}},{"source":"..\\node_modules\\antd\\lib\\input\\index.js","original":{"line":29,"column":0},"generated":{"line":1,"column":370}}],"sources":{"..\\node_modules\\antd\\lib\\input\\index.js":"'use strict';\n\nObject.defineProperty(exports, \"__esModule\", {\n  value: true\n});\n\nvar _Input = require('./Input');\n\nvar _Input2 = _interopRequireDefault(_Input);\n\nvar _Group = require('./Group');\n\nvar _Group2 = _interopRequireDefault(_Group);\n\nvar _Search = require('./Search');\n\nvar _Search2 = _interopRequireDefault(_Search);\n\nvar _TextArea = require('./TextArea');\n\nvar _TextArea2 = _interopRequireDefault(_TextArea);\n\nfunction _interopRequireDefault(obj) { return obj && obj.__esModule ? obj : { 'default': obj }; }\n\n_Input2['default'].Group = _Group2['default'];\n_Input2['default'].Search = _Search2['default'];\n_Input2['default'].TextArea = _TextArea2['default'];\nexports['default'] = _Input2['default'];\nmodule.exports = exports['default'];"},"lineCount":null}},"hash":"55dec834895ff9b39bdc0706aaff07a2","cacheData":{"env":{}}}