{"id":"pR+P","dependencies":[{"name":"E:\\frontend\\CyberMonitor\\node_modules\\lodash-decorators\\package.json","includedInParent":true,"mtime":1535413512217},{"name":"E:\\frontend\\CyberMonitor\\package.json","includedInParent":true,"mtime":1535909131860},{"name":"E:\\frontend\\CyberMonitor\\.babelrc","includedInParent":true,"mtime":1535686769026},{"name":"tslib","loc":{"line":3,"column":22},"parent":"E:\\frontend\\CyberMonitor\\node_modules\\lodash-decorators\\applicators\\PartialApplicator.js","resolved":"E:\\frontend\\CyberMonitor\\node_modules\\tslib\\tslib.es6.js"},{"name":"./Applicator","loc":{"line":4,"column":27},"parent":"E:\\frontend\\CyberMonitor\\node_modules\\lodash-decorators\\applicators\\PartialApplicator.js","resolved":"E:\\frontend\\CyberMonitor\\node_modules\\lodash-decorators\\applicators\\Applicator.js"},{"name":"../utils","loc":{"line":5,"column":22},"parent":"E:\\frontend\\CyberMonitor\\node_modules\\lodash-decorators\\applicators\\PartialApplicator.js","resolved":"E:\\frontend\\CyberMonitor\\node_modules\\lodash-decorators\\utils.js"}],"generated":{"js":"\"use strict\";Object.defineProperty(exports,\"__esModule\",{value:!0});var t=require(\"tslib\"),e=require(\"./Applicator\"),r=require(\"../utils\"),i=function(e){function i(){return null!==e&&e.apply(this,arguments)||this}return t.__extends(i,e),i.prototype.apply=function(t){var e=t.args,i=t.target,n=t.config.execute;return function(){for(var t=[],o=0;o<arguments.length;o++)t[o]=arguments[o];return n.apply(void 0,[r.resolveFunction(e[0],this,i)].concat(e.slice(1))).apply(this,t)}},i}(e.Applicator);exports.PartialApplicator=i;","map":{"mappings":[{"source":"..\\node_modules\\lodash-decorators\\applicators\\PartialApplicator.js","original":{"line":1,"column":0},"generated":{"line":1,"column":0}},{"source":"..\\node_modules\\lodash-decorators\\applicators\\PartialApplicator.js","name":"Object","original":{"line":2,"column":0},"generated":{"line":1,"column":13}},{"source":"..\\node_modules\\lodash-decorators\\applicators\\PartialApplicator.js","name":"defineProperty","original":{"line":2,"column":7},"generated":{"line":1,"column":20}},{"source":"..\\node_modules\\lodash-decorators\\applicators\\PartialApplicator.js","name":"exports","original":{"line":2,"column":22},"generated":{"line":1,"column":35}},{"source":"..\\node_modules\\lodash-decorators\\applicators\\PartialApplicator.js","original":{"line":2,"column":31},"generated":{"line":1,"column":43}},{"source":"..\\node_modules\\lodash-decorators\\applicators\\PartialApplicator.js","original":{"line":2,"column":45},"generated":{"line":1,"column":56}},{"source":"..\\node_modules\\lodash-decorators\\applicators\\PartialApplicator.js","name":"value","original":{"line":2,"column":47},"generated":{"line":1,"column":57}},{"source":"..\\node_modules\\lodash-decorators\\applicators\\PartialApplicator.js","original":{"line":2,"column":54},"generated":{"line":1,"column":64}},{"source":"..\\node_modules\\lodash-decorators\\applicators\\PartialApplicator.js","original":{"line":3,"column":0},"generated":{"line":1,"column":68}},{"source":"..\\node_modules\\lodash-decorators\\applicators\\PartialApplicator.js","name":"tslib_1","original":{"line":3,"column":4},"generated":{"line":1,"column":72}},{"source":"..\\node_modules\\lodash-decorators\\applicators\\PartialApplicator.js","name":"require","original":{"line":3,"column":14},"generated":{"line":1,"column":74}},{"source":"..\\node_modules\\lodash-decorators\\applicators\\PartialApplicator.js","original":{"line":3,"column":22},"generated":{"line":1,"column":82}},{"source":"..\\node_modules\\lodash-decorators\\applicators\\PartialApplicator.js","name":"Applicator_1","original":{"line":4,"column":4},"generated":{"line":1,"column":91}},{"source":"..\\node_modules\\lodash-decorators\\applicators\\PartialApplicator.js","name":"require","original":{"line":4,"column":19},"generated":{"line":1,"column":93}},{"source":"..\\node_modules\\lodash-decorators\\applicators\\PartialApplicator.js","original":{"line":4,"column":27},"generated":{"line":1,"column":101}},{"source":"..\\node_modules\\lodash-decorators\\applicators\\PartialApplicator.js","name":"utils_1","original":{"line":5,"column":4},"generated":{"line":1,"column":117}},{"source":"..\\node_modules\\lodash-decorators\\applicators\\PartialApplicator.js","name":"require","original":{"line":5,"column":14},"generated":{"line":1,"column":119}},{"source":"..\\node_modules\\lodash-decorators\\applicators\\PartialApplicator.js","original":{"line":5,"column":22},"generated":{"line":1,"column":127}},{"source":"..\\node_modules\\lodash-decorators\\applicators\\PartialApplicator.js","name":"PartialApplicator","original":{"line":6,"column":4},"generated":{"line":1,"column":139}},{"source":"..\\node_modules\\lodash-decorators\\applicators\\PartialApplicator.js","original":{"line":6,"column":25},"generated":{"line":1,"column":141}},{"source":"..\\node_modules\\lodash-decorators\\applicators\\PartialApplicator.js","name":"_super","original":{"line":6,"column":35},"generated":{"line":1,"column":150}},{"source":"..\\node_modules\\lodash-decorators\\applicators\\PartialApplicator.js","name":"PartialApplicator","original":{"line":8,"column":13},"generated":{"line":1,"column":153}},{"source":"..\\node_modules\\lodash-decorators\\applicators\\PartialApplicator.js","name":"PartialApplicator","original":{"line":8,"column":13},"generated":{"line":1,"column":162}},{"source":"..\\node_modules\\lodash-decorators\\applicators\\PartialApplicator.js","name":"_super","original":{"line":9,"column":15},"generated":{"line":1,"column":166}},{"source":"..\\node_modules\\lodash-decorators\\applicators\\PartialApplicator.js","original":{"line":9,"column":26},"generated":{"line":1,"column":173}},{"source":"..\\node_modules\\lodash-decorators\\applicators\\PartialApplicator.js","name":"_super","original":{"line":9,"column":15},"generated":{"line":1,"column":180}},{"source":"..\\node_modules\\lodash-decorators\\applicators\\PartialApplicator.js","name":"_super","original":{"line":9,"column":34},"generated":{"line":1,"column":183}},{"source":"..\\node_modules\\lodash-decorators\\applicators\\PartialApplicator.js","name":"apply","original":{"line":9,"column":41},"generated":{"line":1,"column":185}},{"source":"..\\node_modules\\lodash-decorators\\applicators\\PartialApplicator.js","original":{"line":9,"column":47},"generated":{"line":1,"column":191}},{"source":"..\\node_modules\\lodash-decorators\\applicators\\PartialApplicator.js","name":"arguments","original":{"line":9,"column":53},"generated":{"line":1,"column":196}},{"source":"..\\node_modules\\lodash-decorators\\applicators\\PartialApplicator.js","original":{"line":9,"column":67},"generated":{"line":1,"column":208}},{"source":"..\\node_modules\\lodash-decorators\\applicators\\PartialApplicator.js","name":"PartialApplicator","original":{"line":21,"column":11},"generated":{"line":1,"column":213}},{"source":"..\\node_modules\\lodash-decorators\\applicators\\PartialApplicator.js","name":"__extends","original":{"line":7,"column":12},"generated":{"line":1,"column":220}},{"source":"..\\node_modules\\lodash-decorators\\applicators\\PartialApplicator.js","name":"__extends","original":{"line":7,"column":12},"generated":{"line":1,"column":222}},{"source":"..\\node_modules\\lodash-decorators\\applicators\\PartialApplicator.js","name":"PartialApplicator","original":{"line":7,"column":22},"generated":{"line":1,"column":232}},{"source":"..\\node_modules\\lodash-decorators\\applicators\\PartialApplicator.js","name":"_super","original":{"line":7,"column":41},"generated":{"line":1,"column":234}},{"source":"..\\node_modules\\lodash-decorators\\applicators\\PartialApplicator.js","name":"prototype","original":{"line":11,"column":22},"generated":{"line":1,"column":237}},{"source":"..\\node_modules\\lodash-decorators\\applicators\\PartialApplicator.js","name":"prototype","original":{"line":11,"column":22},"generated":{"line":1,"column":239}},{"source":"..\\node_modules\\lodash-decorators\\applicators\\PartialApplicator.js","name":"apply","original":{"line":11,"column":32},"generated":{"line":1,"column":249}},{"source":"..\\node_modules\\lodash-decorators\\applicators\\PartialApplicator.js","original":{"line":11,"column":40},"generated":{"line":1,"column":255}},{"source":"..\\node_modules\\lodash-decorators\\applicators\\PartialApplicator.js","name":"_a","original":{"line":11,"column":50},"generated":{"line":1,"column":264}},{"source":"..\\node_modules\\lodash-decorators\\applicators\\PartialApplicator.js","name":"args","original":{"line":12,"column":12},"generated":{"line":1,"column":267}},{"source":"..\\node_modules\\lodash-decorators\\applicators\\PartialApplicator.js","name":"args","original":{"line":12,"column":12},"generated":{"line":1,"column":271}},{"source":"..\\node_modules\\lodash-decorators\\applicators\\PartialApplicator.js","name":"_a","original":{"line":12,"column":19},"generated":{"line":1,"column":273}},{"source":"..\\node_modules\\lodash-decorators\\applicators\\PartialApplicator.js","name":"args","original":{"line":12,"column":22},"generated":{"line":1,"column":275}},{"source":"..\\node_modules\\lodash-decorators\\applicators\\PartialApplicator.js","name":"target","original":{"line":12,"column":28},"generated":{"line":1,"column":280}},{"source":"..\\node_modules\\lodash-decorators\\applicators\\PartialApplicator.js","name":"_a","original":{"line":12,"column":37},"generated":{"line":1,"column":282}},{"source":"..\\node_modules\\lodash-decorators\\applicators\\PartialApplicator.js","name":"target","original":{"line":12,"column":40},"generated":{"line":1,"column":284}},{"source":"..\\node_modules\\lodash-decorators\\applicators\\PartialApplicator.js","name":"execute","original":{"line":12,"column":48},"generated":{"line":1,"column":291}},{"source":"..\\node_modules\\lodash-decorators\\applicators\\PartialApplicator.js","name":"_a","original":{"line":12,"column":58},"generated":{"line":1,"column":293}},{"source":"..\\node_modules\\lodash-decorators\\applicators\\PartialApplicator.js","name":"config","original":{"line":12,"column":61},"generated":{"line":1,"column":295}},{"source":"..\\node_modules\\lodash-decorators\\applicators\\PartialApplicator.js","name":"execute","original":{"line":12,"column":68},"generated":{"line":1,"column":302}},{"source":"..\\node_modules\\lodash-decorators\\applicators\\PartialApplicator.js","original":{"line":13,"column":15},"generated":{"line":1,"column":310}},{"source":"..\\node_modules\\lodash-decorators\\applicators\\PartialApplicator.js","original":{"line":13,"column":15},"generated":{"line":1,"column":317}},{"source":"..\\node_modules\\lodash-decorators\\applicators\\PartialApplicator.js","original":{"line":15,"column":17},"generated":{"line":1,"column":328}},{"source":"..\\node_modules\\lodash-decorators\\applicators\\PartialApplicator.js","name":"invokeArgs","original":{"line":14,"column":16},"generated":{"line":1,"column":332}},{"source":"..\\node_modules\\lodash-decorators\\applicators\\PartialApplicator.js","name":"invokeArgs","original":{"line":14,"column":16},"generated":{"line":1,"column":336}},{"source":"..\\node_modules\\lodash-decorators\\applicators\\PartialApplicator.js","original":{"line":14,"column":29},"generated":{"line":1,"column":338}},{"source":"..\\node_modules\\lodash-decorators\\applicators\\PartialApplicator.js","name":"_i","original":{"line":15,"column":21},"generated":{"line":1,"column":341}},{"source":"..\\node_modules\\lodash-decorators\\applicators\\PartialApplicator.js","original":{"line":15,"column":26},"generated":{"line":1,"column":343}},{"source":"..\\node_modules\\lodash-decorators\\applicators\\PartialApplicator.js","name":"_i","original":{"line":15,"column":29},"generated":{"line":1,"column":345}},{"source":"..\\node_modules\\lodash-decorators\\applicators\\PartialApplicator.js","name":"arguments","original":{"line":15,"column":34},"generated":{"line":1,"column":347}},{"source":"..\\node_modules\\lodash-decorators\\applicators\\PartialApplicator.js","name":"length","original":{"line":15,"column":44},"generated":{"line":1,"column":357}},{"source":"..\\node_modules\\lodash-decorators\\applicators\\PartialApplicator.js","name":"_i","original":{"line":15,"column":52},"generated":{"line":1,"column":364}},{"source":"..\\node_modules\\lodash-decorators\\applicators\\PartialApplicator.js","name":"_i","original":{"line":16,"column":27},"generated":{"line":1,"column":368}},{"source":"..\\node_modules\\lodash-decorators\\applicators\\PartialApplicator.js","name":"_i","original":{"line":16,"column":27},"generated":{"line":1,"column":370}},{"source":"..\\node_modules\\lodash-decorators\\applicators\\PartialApplicator.js","name":"arguments","original":{"line":16,"column":33},"generated":{"line":1,"column":373}},{"source":"..\\node_modules\\lodash-decorators\\applicators\\PartialApplicator.js","name":"_i","original":{"line":16,"column":43},"generated":{"line":1,"column":383}},{"source":"..\\node_modules\\lodash-decorators\\applicators\\PartialApplicator.js","name":"execute","original":{"line":18,"column":19},"generated":{"line":1,"column":386}},{"source":"..\\node_modules\\lodash-decorators\\applicators\\PartialApplicator.js","name":"execute","original":{"line":18,"column":19},"generated":{"line":1,"column":393}},{"source":"..\\node_modules\\lodash-decorators\\applicators\\PartialApplicator.js","name":"apply","original":{"line":18,"column":27},"generated":{"line":1,"column":395}},{"source":"..\\node_modules\\lodash-decorators\\applicators\\PartialApplicator.js","original":{"line":18,"column":33},"generated":{"line":1,"column":406}},{"source":"..\\node_modules\\lodash-decorators\\applicators\\PartialApplicator.js","original":{"line":18,"column":41},"generated":{"line":1,"column":408}},{"source":"..\\node_modules\\lodash-decorators\\applicators\\PartialApplicator.js","name":"utils_1","original":{"line":18,"column":42},"generated":{"line":1,"column":409}},{"source":"..\\node_modules\\lodash-decorators\\applicators\\PartialApplicator.js","name":"resolveFunction","original":{"line":18,"column":50},"generated":{"line":1,"column":411}},{"source":"..\\node_modules\\lodash-decorators\\applicators\\PartialApplicator.js","name":"args","original":{"line":18,"column":66},"generated":{"line":1,"column":427}},{"source":"..\\node_modules\\lodash-decorators\\applicators\\PartialApplicator.js","original":{"line":18,"column":71},"generated":{"line":1,"column":429}},{"source":"..\\node_modules\\lodash-decorators\\applicators\\PartialApplicator.js","original":{"line":18,"column":75},"generated":{"line":1,"column":432}},{"source":"..\\node_modules\\lodash-decorators\\applicators\\PartialApplicator.js","name":"target","original":{"line":18,"column":81},"generated":{"line":1,"column":437}},{"source":"..\\node_modules\\lodash-decorators\\applicators\\PartialApplicator.js","name":"concat","original":{"line":18,"column":90},"generated":{"line":1,"column":441}},{"source":"..\\node_modules\\lodash-decorators\\applicators\\PartialApplicator.js","name":"args","original":{"line":18,"column":97},"generated":{"line":1,"column":448}},{"source":"..\\node_modules\\lodash-decorators\\applicators\\PartialApplicator.js","name":"slice","original":{"line":18,"column":102},"generated":{"line":1,"column":450}},{"source":"..\\node_modules\\lodash-decorators\\applicators\\PartialApplicator.js","original":{"line":18,"column":108},"generated":{"line":1,"column":456}},{"source":"..\\node_modules\\lodash-decorators\\applicators\\PartialApplicator.js","name":"apply","original":{"line":18,"column":113},"generated":{"line":1,"column":461}},{"source":"..\\node_modules\\lodash-decorators\\applicators\\PartialApplicator.js","original":{"line":18,"column":119},"generated":{"line":1,"column":467}},{"source":"..\\node_modules\\lodash-decorators\\applicators\\PartialApplicator.js","name":"invokeArgs","original":{"line":18,"column":125},"generated":{"line":1,"column":472}},{"source":"..\\node_modules\\lodash-decorators\\applicators\\PartialApplicator.js","name":"PartialApplicator","original":{"line":21,"column":11},"generated":{"line":1,"column":477}},{"source":"..\\node_modules\\lodash-decorators\\applicators\\PartialApplicator.js","original":{"line":6,"column":25},"generated":{"line":1,"column":479}},{"source":"..\\node_modules\\lodash-decorators\\applicators\\PartialApplicator.js","name":"Applicator_1","original":{"line":22,"column":2},"generated":{"line":1,"column":480}},{"source":"..\\node_modules\\lodash-decorators\\applicators\\PartialApplicator.js","name":"Applicator","original":{"line":22,"column":15},"generated":{"line":1,"column":482}},{"source":"..\\node_modules\\lodash-decorators\\applicators\\PartialApplicator.js","name":"exports","original":{"line":23,"column":0},"generated":{"line":1,"column":494}},{"source":"..\\node_modules\\lodash-decorators\\applicators\\PartialApplicator.js","name":"PartialApplicator","original":{"line":23,"column":8},"generated":{"line":1,"column":502}},{"source":"..\\node_modules\\lodash-decorators\\applicators\\PartialApplicator.js","name":"PartialApplicator","original":{"line":23,"column":28},"generated":{"line":1,"column":520}}],"sources":{"..\\node_modules\\lodash-decorators\\applicators\\PartialApplicator.js":"\"use strict\";\nObject.defineProperty(exports, \"__esModule\", { value: true });\nvar tslib_1 = require(\"tslib\");\nvar Applicator_1 = require(\"./Applicator\");\nvar utils_1 = require(\"../utils\");\nvar PartialApplicator = (function (_super) {\n    tslib_1.__extends(PartialApplicator, _super);\n    function PartialApplicator() {\n        return _super !== null && _super.apply(this, arguments) || this;\n    }\n    PartialApplicator.prototype.apply = function (_a) {\n        var args = _a.args, target = _a.target, execute = _a.config.execute;\n        return function () {\n            var invokeArgs = [];\n            for (var _i = 0; _i < arguments.length; _i++) {\n                invokeArgs[_i] = arguments[_i];\n            }\n            return execute.apply(void 0, [utils_1.resolveFunction(args[0], this, target)].concat(args.slice(1))).apply(this, invokeArgs);\n        };\n    };\n    return PartialApplicator;\n}(Applicator_1.Applicator));\nexports.PartialApplicator = PartialApplicator;\n//# sourceMappingURL=PartialApplicator.js.map"},"lineCount":null}},"hash":"98ead6c0f7670a5838bb4fb578c0b7e5","cacheData":{"env":{}}}