{"id":"777+","dependencies":[{"name":"E:\\frontend\\CyberMonitor\\node_modules\\dom-align\\package.json","includedInParent":true,"mtime":1535288317634},{"name":"E:\\frontend\\CyberMonitor\\package.json","includedInParent":true,"mtime":1535440670724},{"name":"E:\\frontend\\CyberMonitor\\.babelrc","includedInParent":true,"mtime":1535438459855},{"name":"./utils","loc":{"line":1,"column":18},"parent":"E:\\frontend\\CyberMonitor\\node_modules\\dom-align\\es\\isAncestorFixed.js","resolved":"E:\\frontend\\CyberMonitor\\node_modules\\dom-align\\es\\utils.js"}],"generated":{"js":"\"use strict\";Object.defineProperty(exports,\"__esModule\",{value:!0}),exports.default=u;var e=require(\"./utils\"),t=r(e);function r(e){return e&&e.__esModule?e:{default:e}}function u(e){if(t.default.isWindow(e)||9===e.nodeType)return!1;var r=t.default.getDocument(e).body,u=null;for(u=e.parentNode;u&&u!==r;u=u.parentNode){if(\"fixed\"===t.default.css(u,\"position\"))return!0}return!1}","map":{"mappings":[{"source":"..\\node_modules\\dom-align\\es\\isAncestorFixed.js","original":{"line":18,"column":1},"generated":{"line":1,"column":0}},{"source":"..\\node_modules\\dom-align\\es\\isAncestorFixed.js","original":{"line":18,"column":1},"generated":{"line":1,"column":13}},{"source":"..\\node_modules\\dom-align\\es\\isAncestorFixed.js","original":{"line":18,"column":1},"generated":{"line":1,"column":20}},{"source":"..\\node_modules\\dom-align\\es\\isAncestorFixed.js","original":{"line":18,"column":1},"generated":{"line":1,"column":35}},{"source":"..\\node_modules\\dom-align\\es\\isAncestorFixed.js","original":{"line":18,"column":1},"generated":{"line":1,"column":43}},{"source":"..\\node_modules\\dom-align\\es\\isAncestorFixed.js","original":{"line":18,"column":1},"generated":{"line":1,"column":56}},{"source":"..\\node_modules\\dom-align\\es\\isAncestorFixed.js","original":{"line":18,"column":1},"generated":{"line":1,"column":57}},{"source":"..\\node_modules\\dom-align\\es\\isAncestorFixed.js","original":{"line":18,"column":1},"generated":{"line":1,"column":64}},{"source":"..\\node_modules\\dom-align\\es\\isAncestorFixed.js","name":"isAncestorFixed","original":{"line":3,"column":24},"generated":{"line":1,"column":68}},{"source":"..\\node_modules\\dom-align\\es\\isAncestorFixed.js","name":"isAncestorFixed","original":{"line":3,"column":24},"generated":{"line":1,"column":76}},{"source":"..\\node_modules\\dom-align\\es\\isAncestorFixed.js","name":"isAncestorFixed","original":{"line":3,"column":24},"generated":{"line":1,"column":84}},{"source":"..\\node_modules\\dom-align\\es\\isAncestorFixed.js","original":{"line":1,"column":0},"generated":{"line":1,"column":86}},{"source":"..\\node_modules\\dom-align\\es\\isAncestorFixed.js","original":{"line":1,"column":0},"generated":{"line":1,"column":90}},{"source":"..\\node_modules\\dom-align\\es\\isAncestorFixed.js","original":{"line":1,"column":0},"generated":{"line":1,"column":92}},{"source":"..\\node_modules\\dom-align\\es\\isAncestorFixed.js","original":{"line":1,"column":0},"generated":{"line":1,"column":100}},{"source":"..\\node_modules\\dom-align\\es\\isAncestorFixed.js","original":{"line":18,"column":1},"generated":{"line":1,"column":111}},{"source":"..\\node_modules\\dom-align\\es\\isAncestorFixed.js","original":{"line":18,"column":1},"generated":{"line":1,"column":113}},{"source":"..\\node_modules\\dom-align\\es\\isAncestorFixed.js","original":{"line":18,"column":1},"generated":{"line":1,"column":115}},{"source":"..\\node_modules\\dom-align\\es\\isAncestorFixed.js","original":{"line":18,"column":1},"generated":{"line":1,"column":118}},{"source":"..\\node_modules\\dom-align\\es\\isAncestorFixed.js","original":{"line":18,"column":1},"generated":{"line":1,"column":127}},{"source":"..\\node_modules\\dom-align\\es\\isAncestorFixed.js","original":{"line":18,"column":1},"generated":{"line":1,"column":129}},{"source":"..\\node_modules\\dom-align\\es\\isAncestorFixed.js","original":{"line":18,"column":1},"generated":{"line":1,"column":132}},{"source":"..\\node_modules\\dom-align\\es\\isAncestorFixed.js","original":{"line":18,"column":1},"generated":{"line":1,"column":139}},{"source":"..\\node_modules\\dom-align\\es\\isAncestorFixed.js","original":{"line":18,"column":1},"generated":{"line":1,"column":142}},{"source":"..\\node_modules\\dom-align\\es\\isAncestorFixed.js","original":{"line":18,"column":1},"generated":{"line":1,"column":144}},{"source":"..\\node_modules\\dom-align\\es\\isAncestorFixed.js","original":{"line":18,"column":1},"generated":{"line":1,"column":155}},{"source":"..\\node_modules\\dom-align\\es\\isAncestorFixed.js","original":{"line":18,"column":1},"generated":{"line":1,"column":157}},{"source":"..\\node_modules\\dom-align\\es\\isAncestorFixed.js","original":{"line":18,"column":1},"generated":{"line":1,"column":158}},{"source":"..\\node_modules\\dom-align\\es\\isAncestorFixed.js","original":{"line":18,"column":1},"generated":{"line":1,"column":166}},{"source":"..\\node_modules\\dom-align\\es\\isAncestorFixed.js","original":{"line":3,"column":15},"generated":{"line":1,"column":169}},{"source":"..\\node_modules\\dom-align\\es\\isAncestorFixed.js","name":"isAncestorFixed","original":{"line":3,"column":24},"generated":{"line":1,"column":178}},{"source":"..\\node_modules\\dom-align\\es\\isAncestorFixed.js","name":"element","original":{"line":3,"column":40},"generated":{"line":1,"column":180}},{"source":"..\\node_modules\\dom-align\\es\\isAncestorFixed.js","name":"utils","original":{"line":4,"column":6},"generated":{"line":1,"column":183}},{"source":"..\\node_modules\\dom-align\\es\\isAncestorFixed.js","name":"utils","original":{"line":4,"column":6},"generated":{"line":1,"column":186}},{"source":"..\\node_modules\\dom-align\\es\\isAncestorFixed.js","name":"isWindow","original":{"line":4,"column":12},"generated":{"line":1,"column":188}},{"source":"..\\node_modules\\dom-align\\es\\isAncestorFixed.js","name":"isWindow","original":{"line":4,"column":12},"generated":{"line":1,"column":196}},{"source":"..\\node_modules\\dom-align\\es\\isAncestorFixed.js","name":"element","original":{"line":4,"column":21},"generated":{"line":1,"column":205}},{"source":"..\\node_modules\\dom-align\\es\\isAncestorFixed.js","original":{"line":4,"column":54},"generated":{"line":1,"column":209}},{"source":"..\\node_modules\\dom-align\\es\\isAncestorFixed.js","name":"element","original":{"line":4,"column":33},"generated":{"line":1,"column":213}},{"source":"..\\node_modules\\dom-align\\es\\isAncestorFixed.js","name":"nodeType","original":{"line":4,"column":41},"generated":{"line":1,"column":215}},{"source":"..\\node_modules\\dom-align\\es\\isAncestorFixed.js","original":{"line":5,"column":11},"generated":{"line":1,"column":224}},{"source":"..\\node_modules\\dom-align\\es\\isAncestorFixed.js","original":{"line":5,"column":11},"generated":{"line":1,"column":231}},{"source":"..\\node_modules\\dom-align\\es\\isAncestorFixed.js","name":"doc","original":{"line":8,"column":6},"generated":{"line":1,"column":233}},{"source":"..\\node_modules\\dom-align\\es\\isAncestorFixed.js","name":"body","original":{"line":9,"column":6},"generated":{"line":1,"column":237}},{"source":"..\\node_modules\\dom-align\\es\\isAncestorFixed.js","name":"utils","original":{"line":8,"column":12},"generated":{"line":1,"column":239}},{"source":"..\\node_modules\\dom-align\\es\\isAncestorFixed.js","name":"getDocument","original":{"line":8,"column":18},"generated":{"line":1,"column":241}},{"source":"..\\node_modules\\dom-align\\es\\isAncestorFixed.js","name":"getDocument","original":{"line":8,"column":18},"generated":{"line":1,"column":249}},{"source":"..\\node_modules\\dom-align\\es\\isAncestorFixed.js","name":"element","original":{"line":8,"column":30},"generated":{"line":1,"column":261}},{"source":"..\\node_modules\\dom-align\\es\\isAncestorFixed.js","name":"body","original":{"line":9,"column":17},"generated":{"line":1,"column":264}},{"source":"..\\node_modules\\dom-align\\es\\isAncestorFixed.js","name":"parent","original":{"line":10,"column":6},"generated":{"line":1,"column":269}},{"source":"..\\node_modules\\dom-align\\es\\isAncestorFixed.js","original":{"line":10,"column":15},"generated":{"line":1,"column":271}},{"source":"..\\node_modules\\dom-align\\es\\isAncestorFixed.js","name":"parent","original":{"line":11,"column":7},"generated":{"line":1,"column":276}},{"source":"..\\node_modules\\dom-align\\es\\isAncestorFixed.js","name":"parent","original":{"line":11,"column":7},"generated":{"line":1,"column":280}},{"source":"..\\node_modules\\dom-align\\es\\isAncestorFixed.js","name":"element","original":{"line":11,"column":16},"generated":{"line":1,"column":282}},{"source":"..\\node_modules\\dom-align\\es\\isAncestorFixed.js","name":"parentNode","original":{"line":11,"column":24},"generated":{"line":1,"column":284}},{"source":"..\\node_modules\\dom-align\\es\\isAncestorFixed.js","name":"parent","original":{"line":11,"column":36},"generated":{"line":1,"column":295}},{"source":"..\\node_modules\\dom-align\\es\\isAncestorFixed.js","name":"parent","original":{"line":11,"column":46},"generated":{"line":1,"column":298}},{"source":"..\\node_modules\\dom-align\\es\\isAncestorFixed.js","name":"body","original":{"line":11,"column":57},"generated":{"line":1,"column":302}},{"source":"..\\node_modules\\dom-align\\es\\isAncestorFixed.js","name":"parent","original":{"line":11,"column":63},"generated":{"line":1,"column":304}},{"source":"..\\node_modules\\dom-align\\es\\isAncestorFixed.js","name":"parent","original":{"line":11,"column":72},"generated":{"line":1,"column":306}},{"source":"..\\node_modules\\dom-align\\es\\isAncestorFixed.js","name":"parentNode","original":{"line":11,"column":79},"generated":{"line":1,"column":308}},{"source":"..\\node_modules\\dom-align\\es\\isAncestorFixed.js","original":{"line":11,"column":91},"generated":{"line":1,"column":319}},{"source":"..\\node_modules\\dom-align\\es\\isAncestorFixed.js","name":"positionStyle","original":{"line":13,"column":8},"generated":{"line":1,"column":320}},{"source":"..\\node_modules\\dom-align\\es\\isAncestorFixed.js","original":{"line":13,"column":26},"generated":{"line":1,"column":323}},{"source":"..\\node_modules\\dom-align\\es\\isAncestorFixed.js","name":"utils","original":{"line":12,"column":24},"generated":{"line":1,"column":333}},{"source":"..\\node_modules\\dom-align\\es\\isAncestorFixed.js","name":"css","original":{"line":12,"column":30},"generated":{"line":1,"column":335}},{"source":"..\\node_modules\\dom-align\\es\\isAncestorFixed.js","name":"css","original":{"line":12,"column":30},"generated":{"line":1,"column":343}},{"source":"..\\node_modules\\dom-align\\es\\isAncestorFixed.js","name":"parent","original":{"line":12,"column":34},"generated":{"line":1,"column":347}},{"source":"..\\node_modules\\dom-align\\es\\isAncestorFixed.js","original":{"line":12,"column":42},"generated":{"line":1,"column":349}},{"source":"..\\node_modules\\dom-align\\es\\isAncestorFixed.js","original":{"line":14,"column":13},"generated":{"line":1,"column":361}},{"source":"..\\node_modules\\dom-align\\es\\isAncestorFixed.js","original":{"line":14,"column":13},"generated":{"line":1,"column":368}},{"source":"..\\node_modules\\dom-align\\es\\isAncestorFixed.js","original":{"line":17,"column":9},"generated":{"line":1,"column":370}},{"source":"..\\node_modules\\dom-align\\es\\isAncestorFixed.js","original":{"line":17,"column":9},"generated":{"line":1,"column":377}}],"sources":{"..\\node_modules\\dom-align\\es\\isAncestorFixed.js":"import utils from './utils';\n\nexport default function isAncestorFixed(element) {\n  if (utils.isWindow(element) || element.nodeType === 9) {\n    return false;\n  }\n\n  var doc = utils.getDocument(element);\n  var body = doc.body;\n  var parent = null;\n  for (parent = element.parentNode; parent && parent !== body; parent = parent.parentNode) {\n    var positionStyle = utils.css(parent, 'position');\n    if (positionStyle === 'fixed') {\n      return true;\n    }\n  }\n  return false;\n}"},"lineCount":null}},"hash":"4d1d4682df357409d4395d84a42f9d6d","cacheData":{"env":{}}}